{
    "全部分类": [],
    "2024年评价最佳": [],
    "2023年评价最佳": [],
    "2022年评价最佳": [],
    "2021年评价最佳": [],
    "2020年评价最佳": [],
    "本月热门🔥🔞": [],
    "2025年新片已阅推荐✨🌅🧡": [],
    "综合分类破万人收藏🧸ྀི": [],
    "综合分类破2万人收藏🧸ྀི": [],
    "综合分类破3万人收藏🧸ྀི": [],
    "夫妻交换🎎": "",
    "出轨🍷": [],
    "巨乳🐻": [],
    "人妻👰": [],
    "泳装👙": [],
    "健身🥵": [],
    "多P👥": [],
    "丝袜🧦": [],
    "未亡人👘": [],
    "老师🧑‍🏫": [],
    "口爆👅": [],
    "制服诱惑👩🏻‍💼": [],
    "肉漫改编✍️": [],
    "办公室🤤": [],
    "综合●": [],
    "友人の●": "",
    "父●": [],
    "母●": [],
    "姐●": []
}